setup.py
guassian_binomial_distribution_probability/Binomialdistribution.py
guassian_binomial_distribution_probability/Gaussiandistribution.py
guassian_binomial_distribution_probability/Generaldistribution.py
guassian_binomial_distribution_probability/__init__.py
guassian_binomial_distribution_probability.egg-info/PKG-INFO
guassian_binomial_distribution_probability.egg-info/SOURCES.txt
guassian_binomial_distribution_probability.egg-info/dependency_links.txt
guassian_binomial_distribution_probability.egg-info/not-zip-safe
guassian_binomial_distribution_probability.egg-info/top_level.txt