Metadata-Version: 1.0
Name: guassian-binomial-distribution-probability
Version: 1.0
Summary: Gaussian and Binomial distributions
Home-page: UNKNOWN
Author: Vinodh Kumar
Author-email: myemail@somthing.com
License: UNKNOWN
Platform: UNKNOWN
